substrateinterface_polkascan/__init__.py
substrateinterface_polkascan/extensions.py
substrate_interface_polkascan-0.2.dist-info/LICENSE
substrate_interface_polkascan-0.2.dist-info/METADATA
substrate_interface_polkascan-0.2.dist-info/WHEEL
substrate_interface_polkascan-0.2.dist-info/top_level.txt
substrate_interface_polkascan-0.2.dist-info/RECORD
